{
  "address": "0.1.11.4.0.1.11.3.745",
  "type_address": null,
  "data": {
    "name": "745",
    "type": "folder",
    "path": "C:\\Hypernet\\Hypernet Structure\\0\\0.1 - Hypernet Core\\data\\nodes\\0\\1\\11\\3\\745",
    "content": "{\n  \"address\": \"0.1.11.3.745\",\n  \"type_address\": null,\n  \"data\": {\n    \"name\": \"94b0a077292a4e03.json\",\n    \"type\": \"file\",\n    \"extension\": \".json\",\n    \"path\": \"C:\\\\Hypernet\\\\Hypernet Structure\\\\0\\\\0.1 - Hypernet Core\\\\data\\\\links\\\\94b0a077292a4e03.json\",\n    \"size\": 281,\n    \"content\": \"{\\n  \\\"from_address\\\": \\\"0.1.11.3\\\",\\n  \\\"to_address\\\": \\\"0.1.11.3.111\\\",\\n  \\\"link_type\\\": \\\"0.6.3\\\",\\n  \\\"relationship\\\": \\\"contains\\\",\\n  \\\"address\\\": null,\\n  \\\"strength\\\": 1.0,\\n  \\\"bidirectional\\\": false,\\n  \\\"data\\\": {},\\n  \\\"created_at\\\": \\\"2026-02-17T01:20:07.474957+00:00\\\",\\n  \\\"sort_order\\\": null\\n}\"\n  },\n  \"created_at\": \"2026-02-17T01:22:12.721577+00:00\",\n  \"updated_at\": \"2026-02-17T01:22:12.721577+00:00\",\n  \"deleted_at\": null,\n  \"source_type\": \"import\",\n  \"source_id\": \"file:94b0a077292a4e03.json\"\n}",
    "content_file": "node.json"
  },
  "created_at": "2026-02-17T01:22:43.427277+00:00",
  "updated_at": "2026-02-17T01:22:43.427277+00:00",
  "deleted_at": null,
  "source_type": "import",
  "source_id": "folder:745"
}