{
  "version": 1,
  "content_hash": "681066c739de7fbe",
  "snapshot_at": "2026-02-17T01:22:33.989290+00:00",
  "node": {
    "address": "0.1.11.4.0.1.11.3.2",
    "type_address": null,
    "data": {
      "name": "2",
      "type": "folder",
      "path": "C:\\Hypernet\\Hypernet Structure\\0\\0.1 - Hypernet Core\\data\\nodes\\0\\1\\11\\3\\2",
      "content": "{\n  \"address\": \"0.1.11.3.2\",\n  \"type_address\": null,\n  \"data\": {\n    \"name\": \"047f160a2e336aee.json\",\n    \"type\": \"file\",\n    \"extension\": \".json\",\n    \"path\": \"C:\\\\Hypernet\\\\Hypernet Structure\\\\0\\\\0.1 - Hypernet Core\\\\data\\\\links\\\\047f160a2e336aee.json\",\n    \"size\": 274,\n    \"content\": \"{\\n  \\\"from_address\\\": \\\"0.1.0\\\",\\n  \\\"to_address\\\": \\\"0.1.0.12\\\",\\n  \\\"link_type\\\": \\\"0.6.3\\\",\\n  \\\"relationship\\\": \\\"contains\\\",\\n  \\\"address\\\": null,\\n  \\\"strength\\\": 1.0,\\n  \\\"bidirectional\\\": false,\\n  \\\"data\\\": {},\\n  \\\"created_at\\\": \\\"2026-02-17T01:20:04.784091+00:00\\\",\\n  \\\"sort_order\\\": null\\n}\"\n  },\n  \"created_at\": \"2026-02-17T01:20:05.521641+00:00\",\n  \"updated_at\": \"2026-02-17T01:20:05.521641+00:00\",\n  \"deleted_at\": null,\n  \"source_type\": \"import\",\n  \"source_id\": \"file:047f160a2e336aee.json\"\n}",
      "content_file": "node.json"
    },
    "created_at": "2026-02-17T01:20:18.007803+00:00",
    "updated_at": "2026-02-17T01:20:18.007803+00:00",
    "deleted_at": null,
    "source_type": "import",
    "source_id": "folder:2"
  }
}